multiplexer.v
`timescale 1ns/1ps
module two2oneMUX(i0, i1, sel, o);
 input i0, i1, sel;
 output o;
 assign o=(sel==1)?i1:i0;
endmodule
module eight2oneMUX(i0, i1, i2, i3, i4, i5, i6, i7, sel1, sel2, sel3, out);
 input i0, i1, i2, i3, i4, i5, i6, i7, sel1, sel2, sel3;
 output out;
 wire w1, w2, w3, w4, w5, w6, w7;
 two2oneMUX p(i0, i1, sel1, w1);
 two2oneMUX q(i2, i3, sel1, w2);
 two2oneMUX r(i4, i5, sel1, w3);
 two2oneMUX s(i6, i7, sel1, w4);
 two2oneMUX t(w1, w2, sel2, w5);
 two2oneMUX u(w3, w4, sel2, w6);
 two2oneMUX v(w5, w6, sel3, out);
endmodule

multiplexer_tb.v
`timescale 1ns/1ps
module test();
 reg [7:0] i;
 reg a,b,c;
 wire f;
 eight2oneMUX uut (.i0(i[0]), .i1(i[1]), .i2(i[2]), .i3(i[3]), .i4(i[4]), .i5(i[5]), .i6(i[6]), .i7(i[7]), .sel1(a), .sel2(b), .sel3(c), .out(f));
 initial
 begin
    i[0] = 0;
    i[1] = 0;
    i[2] = 0;
    i[3] = 0;
    i[4] = 0;
    i[5] = 0;
    i[6] = 0;
    i[7] = 0;
    a = 0;
    b = 0;
    c = 0;
        $monitor("s : %b %b %b , i : %d :: output = %b", a, b, c, i, f);
    // Waveform generation
        $dumpfile("multiplexer_tb.vcd");  // Waveform file
        $dumpvars(0, test);         // signals to plot (everything)

        // We finish simulation at t=100
        #20480 $finish;
 end
always
    #80 i = i + 1;
always
    #10 a = ~a;
always
    #20 b = ~b;
always
    #40 c = ~c;
endmodule

multiplexer_tb.vcd
$date
	Tue Sep 12 17:26:24 2023
$end
$version
	Icarus Verilog
$end
$timescale
	1ps
$end
$scope module test $end
$var wire 1 ! f $end
$var reg 1 " a $end
$var reg 1 # b $end
$var reg 1 $ c $end
$var reg 8 % i [7:0] $end
$scope module uut $end
$var wire 1 & i0 $end
$var wire 1 ' i1 $end
$var wire 1 ( i2 $end
$var wire 1 ) i3 $end
$var wire 1 * i4 $end
$var wire 1 + i5 $end
$var wire 1 , i6 $end
$var wire 1 - i7 $end
$var wire 1 " sel1 $end
$var wire 1 # sel2 $end
$var wire 1 $ sel3 $end
$var wire 1 . w6 $end
$var wire 1 / w5 $end
$var wire 1 0 w4 $end
$var wire 1 1 w3 $end
$var wire 1 2 w2 $end
$var wire 1 3 w1 $end
$var wire 1 ! out $end
$scope module p $end
$var wire 1 & i0 $end
$var wire 1 ' i1 $end
$var wire 1 " sel $end
$var wire 1 3 o $end
$upscope $end
$scope module q $end
$var wire 1 ( i0 $end
$var wire 1 ) i1 $end
$var wire 1 " sel $end
$var wire 1 2 o $end
$upscope $end
$scope module r $end
$var wire 1 * i0 $end
$var wire 1 + i1 $end
$var wire 1 " sel $end
$var wire 1 1 o $end
$upscope $end
$scope module s $end
$var wire 1 , i0 $end
$var wire 1 - i1 $end
$var wire 1 " sel $end
$var wire 1 0 o $end
$upscope $end
$scope module t $end
$var wire 1 3 i0 $end
$var wire 1 2 i1 $end
$var wire 1 # sel $end
$var wire 1 / o $end
$upscope $end
$scope module u $end
$var wire 1 1 i0 $end
$var wire 1 0 i1 $end
$var wire 1 # sel $end
$var wire 1 . o $end
$upscope $end
$scope module v $end
$var wire 1 / i0 $end
$var wire 1 . i1 $end
$var wire 1 $ sel $end
$var wire 1 ! o $end
$upscope $end
$upscope $end
$upscope $end
$enddefinitions $end
#0
$dumpvars
03
02
01
00
0/
0.
0-
0,
0+
0*
0)
0(
0'
0&
b0 %
0$
0#
0"
0!
$end
#10000
1"
#20000
0"
1#
#30000
1"
#40000
0"
0#
1$
#50000
1"
#60000
0"
1#
#70000
1"
#80000
1!
1/
13
1&
0"
0#
0$
b1 %
#90000
0!
0/
03
1"
#100000
13
0"
1#
#110000
03
1"
#120000
1/
13
0"
0#
1$
#130000
0/
03
1"
#140000
13
0"
1#
#150000
03
1"
#160000
0&
1'
0"
0#
0$
b10 %
#170000
1!
1/
13
1"
#180000
0!
03
0/
0"
1#
#190000
13
1"
#200000
03
0/
0"
0#
1$
#210000
1/
13
1"
#220000
03
0/
0"
1#
#230000
13
1"
#240000
1!
1/
1&
0"
0#
0$
b11 %
#250000
1"
#260000
0!
0/
0"
1#
#270000
1"
#280000
1/
0"
0#
1$
#290000
1"
#300000
0/
0"
1#
#310000
1"
#320000
0!
03
12
0/
0&
0'
1(
0"
0#
0$
b100 %
#330000
02
1"
#340000
1!
1/
12
0"
1#
#350000
0!
0/
02
1"
#360000
12
0"
0#
1$
#370000
02
1"
#380000
1/
12
0"
1#
#390000
0/
02
1"
#400000
1!
1/
13
12
1&
0"
0#
0$
b101 %
#410000
0!
0/
03
02
1"
#420000
1!
1/
13
12
0"
1#
#430000
0!
0/
03
02
1"
#440000
1/
13
12
0"
0#
1$
#450000
0/
03
02
1"
#460000
1/
13
12
0"
1#
#470000
0/
03
02
1"
#480000
12
0&
1'
0"
0#
0$
b110 %
#490000
1!
1/
13
02
1"
#500000
1!
03
12
1/
0"
1#
#510000
0!
0/
13
02
1"
#520000
03
12
0/
0"
0#
1$
#530000
1/
13
02
1"
#540000
03
12
1/
0"
1#
#550000
0/
13
02
1"
#560000
1!
12
1/
1&
0"
0#
0$
b111 %
#570000
02
1"
#580000
1!
12
1/
0"
1#
#590000
0!
0/
02
1"
#600000
12
1/
0"
0#
1$
#610000
02
1"
#620000
12
1/
0"
1#
#630000
0/
02
1"
#640000
0!
03
0/
0&
0'
0(
1)
0"
0#
0$
b1000 %
#650000
12
1"
#660000
0!
02
0/
0"
1#
#670000
1!
1/
12
1"
#680000
02
0/
0!
0"
0#
1$
#690000
12
1"
#700000
02
0/
0"
1#
#710000
1/
12
1"
#720000
13
02
1/
1!
1&
0"
0#
0$
b1001 %
#730000
0!
0/
03
12
1"
#740000
0!
13
02
0/
0"
1#
#750000
1!
1/
03
12
1"
#760000
13
02
1/
0!
0"
0#
1$
#770000
0/
03
12
1"
#780000
13
02
0/
0"
1#
#790000
1/
03
12
1"
#800000
02
0/
0!
0&
1'
0"
0#
0$
b1010 %
#810000
1!
1/
13
12
1"
#820000
0!
0/
03
02
0"
1#
#830000
1!
1/
13
12
1"
#840000
0/
03
02
0!
0"
0#
1$
#850000
1/
13
12
1"
#860000
0/
03
02
0"
1#
#870000
1/
13
12
1"
#880000
02
1!
1&
0"
0#
0$
b1011 %
#890000
12
1"
#900000
0!
0/
02
0"
1#
#910000
1!
1/
12
1"
#920000
02
0!
0"
0#
1$
#930000
12
1"
#940000
0/
02
0"
1#
#950000
1/
12
1"
#960000
0/
03
0!
0&
0'
1(
0"
0#
0$
b1100 %
#970000
1"
#980000
1!
1/
0"
1#
#990000
1"
#1000000
0/
0!
0"
0#
1$
#1010000
1"
#1020000
1/
0"
1#
#1030000
1"
#1040000
13
1/
1!
1&
0"
0#
0$
b1101 %
#1050000
0!
0/
03
1"
#1060000
1!
13
1/
0"
1#
#1070000
03
1"
#1080000
13
1/
0!
0"
0#
1$
#1090000
0/
03
1"
#1100000
13
1/
0"
1#
#1110000
03
1"
#1120000
0/
0!
0&
1'
0"
0#
0$
b1110 %
#1130000
1!
1/
13
1"
#1140000
03
0"
1#
#1150000
13
1"
#1160000
0/
03
0!
0"
0#
1$
#1170000
1/
13
1"
#1180000
03
0"
1#
#1190000
13
1"
#1200000
1!
1&
0"
0#
0$
b1111 %
#1210000
1"
#1220000
0"
1#
#1230000
1"
#1240000
0!
0"
0#
1$
#1250000
1"
#1260000
0"
1#
#1270000
1"
#1280000
0/
1.
03
02
11
0!
0&
0'
0(
0)
1*
0"
0#
0$
b10000 %
#1290000
0.
01
1"
#1300000
11
0"
1#
#1310000
01
1"
#1320000
1!
1.
11
0"
0#
1$
#1330000
0!
0.
01
1"
#1340000
11
0"
1#
#1350000
01
1"
#1360000
1!
1/
1.
13
11
1&
0"
0#
0$
b10001 %
#1370000
0!
0/
0.
03
01
1"
#1380000
13
11
0"
1#
#1390000
03
01
1"
#1400000
1!
1/
1.
13
11
0"
0#
1$
#1410000
0!
0/
0.
03
01
1"
#1420000
13
11
0"
1#
#1430000
03
01
1"
#1440000
1.
11
0&
1'
0"
0#
0$
b10010 %
#1450000
1!
1/
0.
13
01
1"
#1460000
0!
03
11
0/
0"
1#
#1470000
13
01
1"
#1480000
1!
1.
03
11
0/
0"
0#
1$
#1490000
0!
1/
0.
13
01
1"
#1500000
03
11
0/
0"
1#
#1510000
13
01
1"
#1520000
1.
1!
11
1/
1&
0"
0#
0$
b10011 %
#1530000
0.
01
1"
#1540000
0!
11
0/
0"
1#
#1550000
01
1"
#1560000
1!
1.
11
1/
0"
0#
1$
#1570000
0!
0.
01
1"
#1580000
11
0/
0"
1#
#1590000
01
1"
#1600000
1.
0!
03
12
11
0/
0&
0'
1(
0"
0#
0$
b10100 %
#1610000
0.
02
01
1"
#1620000
1!
1/
12
11
0"
1#
#1630000
0!
0/
02
01
1"
#1640000
1!
1.
12
11
0"
0#
1$
#1650000
0!
0.
02
01
1"
#1660000
1/
12
11
0"
1#
#1670000
0/
02
01
1"
#1680000
1!
1/
1.
13
12
11
1&
0"
0#
0$
b10101 %
#1690000
0!
0/
0.
03
02
01
1"
#1700000
1!
1/
13
12
11
0"
1#
#1710000
0!
0/
03
02
01
1"
#1720000
1!
1/
1.
13
12
11
0"
0#
1$
#1730000
0!
0/
0.
03
02
01
1"
#1740000
1/
13
12
11
0"
1#
#1750000
0/
03
02
01
1"
#1760000
1.
12
11
0&
1'
0"
0#
0$
b10110 %
#1770000
1!
1/
0.
13
02
01
1"
#1780000
1!
03
12
11
1/
0"
1#
#1790000
0!
0/
13
02
01
1"
#1800000
1!
1.
03
12
11
0/
0"
0#
1$
#1810000
0!
1/
0.
13
02
01
1"
#1820000
03
12
11
1/
0"
1#
#1830000
0/
13
02
01
1"
#1840000
1.
1!
12
11
1/
1&
0"
0#
0$
b10111 %
#1850000
0.
02
01
1"
#1860000
1!
12
11
1/
0"
1#
#1870000
0!
0/
02
01
1"
#1880000
1!
1.
12
11
1/
0"
0#
1$
#1890000
0!
0.
02
01
1"
#1900000
12
11
1/
0"
1#
#1910000
0/
02
01
1"
#1920000
1.
0!
03
11
0/
0&
0'
0(
1)
0"
0#
0$
b11000 %
#1930000
0.
12
01
1"
#1940000
0!
02
11
0/
0"
1#
#1950000
1!
1/
12
01
1"
#1960000
1.
02
11
0/
1!
0"
0#
1$
#1970000
0!
0.
12
01
1"
#1980000
02
11
0/
0"
1#
#1990000
1/
12
01
1"
#2000000
1.
13
02
11
1/
1!
1&
0"
0#
0$
b11001 %
#2010000
0!
0/
0.
03
12
01
1"
#2020000
0!
13
02
11
0/
0"
1#
#2030000
1!
1/
03
12
01
1"
#2040000
1.
13
02
11
1/
1!
0"
0#
1$
#2050000
0!
0/
0.
03
12
01
1"
#2060000
13
02
11
0/
0"
1#
#2070000
1/
03
12
01
1"
#2080000
1.
02
11
0/
0!
0&
1'
0"
0#
0$
b11010 %
#2090000
1!
1/
0.
13
12
01
1"
#2100000
0!
0/
03
02
11
0"
1#
#2110000
1!
1/
13
12
01
1"
#2120000
0/
1.
03
02
11
1!
0"
0#
1$
#2130000
0!
1/
0.
13
12
01
1"
#2140000
0/
03
02
11
0"
1#
#2150000
1/
13
12
01
1"
#2160000
1.
02
11
1!
1&
0"
0#
0$
b11011 %
#2170000
0.
12
01
1"
#2180000
0!
0/
02
11
0"
1#
#2190000
1!
1/
12
01
1"
#2200000
1.
02
11
1!
0"
0#
1$
#2210000
0!
0.
12
01
1"
#2220000
0/
02
11
0"
1#
#2230000
1/
12
01
1"
#2240000
0/
1.
03
11
0!
0&
0'
1(
0"
0#
0$
b11100 %
#2250000
0.
01
1"
#2260000
1!
11
1/
0"
1#
#2270000
01
1"
#2280000
1.
11
0/
1!
0"
0#
1$
#2290000
0!
0.
01
1"
#2300000
11
1/
0"
1#
#2310000
01
1"
#2320000
1.
13
11
1/
1!
1&
0"
0#
0$
b11101 %
#2330000
0!
0/
0.
03
01
1"
#2340000
1!
13
11
1/
0"
1#
#2350000
03
01
1"
#2360000
1.
13
11
1/
1!
0"
0#
1$
#2370000
0!
0/
0.
03
01
1"
#2380000
13
11
1/
0"
1#
#2390000
03
01
1"
#2400000
1.
11
0/
0!
0&
1'
0"
0#
0$
b11110 %
#2410000
1!
1/
0.
13
01
1"
#2420000
03
11
0"
1#
#2430000
13
01
1"
#2440000
0/
1.
03
11
1!
0"
0#
1$
#2450000
0!
1/
0.
13
01
1"
#2460000
03
11
0"
1#
#2470000
13
01
1"
#2480000
1.
11
1!
1&
0"
0#
0$
b11111 %
#2490000
0.
01
1"
#2500000
11
0"
1#
#2510000
01
1"
#2520000
1.
11
1!
0"
0#
1$
#2530000
0!
0.
01
1"
#2540000
11
0"
1#
#2550000
01
1"
#2560000
0/
03
02
0!
0&
0'
0(
0)
0*
1+
0"
0#
0$
b100000 %
#2570000
1.
11
1"
#2580000
01
0.
0"
1#
#2590000
11
1"
#2600000
0!
01
0.
0"
0#
1$
#2610000
1!
1.
11
1"
#2620000
0!
01
0.
0"
1#
#2630000
11
1"
#2640000
1!
1/
13
01
0.
1&
0"
0#
0$
b100001 %
#2650000
0!
0/
1.
03
11
1"
#2660000
13
01
0.
0"
1#
#2670000
03
11
1"
#2680000
1/
0!
13
01
0.
0"
0#
1$
#2690000
1!
0/
1.
03
11
1"
#2700000
0!
13
01
0.
0"
1#
#2710000
03
11
1"
#2720000
01
0.
0&
1'
0"
0#
0$
b100010 %
#2730000
1!
1/
1.
13
11
1"
#2740000
0!
03
01
0/
0.
0"
1#
#2750000
13
11
1"
#2760000
0!
03
01
0/
0.
0"
0#
1$
#2770000
1!
1/
1.
13
11
1"
#2780000
0!
03
01
0/
0.
0"
1#
#2790000
13
11
1"
#2800000
1!
01
1/
0.
1&
0"
0#
0$
b100011 %
#2810000
1.
11
1"
#2820000
0!
01
0/
0.
0"
1#
#2830000
11
1"
#2840000
0!
01
1/
0.
0"
0#
1$
#2850000
1!
1.
11
1"
#2860000
0!
01
0/
0.
0"
1#
#2870000
11
1"
#2880000
0!
03
12
01
0/
0.
0&
0'
1(
0"
0#
0$
b100100 %
#2890000
1.
02
11
1"
#2900000
1!
1/
12
01
0.
0"
1#
#2910000
0!
0/
02
11
1"
#2920000
0!
12
01
0.
0"
0#
1$
#2930000
1!
1.
02
11
1"
#2940000
1/
0!
12
01
0.
0"
1#
#2950000
0/
02
11
1"
#2960000
1!
1/
13
12
01
0.
1&
0"
0#
0$
b100101 %
#2970000
0!
0/
1.
03
02
11
1"
#2980000
1!
1/
13
12
01
0.
0"
1#
#2990000
0!
0/
03
02
11
1"
#3000000
1/
0!
13
12
01
0.
0"
0#
1$
#3010000
1!
0/
1.
03
02
11
1"
#3020000
1/
0!
13
12
01
0.
0"
1#
#3030000
0/
03
02
11
1"
#3040000
12
01
0.
0&
1'
0"
0#
0$
b100110 %
#3050000
1!
1/
1.
13
02
11
1"
#3060000
1!
03
12
01
1/
0.
0"
1#
#3070000
0!
0/
13
02
11
1"
#3080000
0!
03
12
01
0/
0.
0"
0#
1$
#3090000
1!
1/
1.
13
02
11
1"
#3100000
0!
03
12
01
1/
0.
0"
1#
#3110000
0/
13
02
11
1"
#3120000
1!
12
01
1/
0.
1&
0"
0#
0$
b100111 %
#3130000
1.
02
11
1"
#3140000
1!
12
01
1/
0.
0"
1#
#3150000
0!
0/
02
11
1"
#3160000
0!
12
01
1/
0.
0"
0#
1$
#3170000
1!
1.
02
11
1"
#3180000
0!
12
01
1/
0.
0"
1#
#3190000
0/
02
11
1"
#3200000
0!
03
01
0/
0.
0&
0'
0(
1)
0"
0#
0$
b101000 %
#3210000
1.
12
11
1"
#3220000
0!
02
01
0/
0.
0"
1#
#3230000
1!
1/
12
11
1"
#3240000
02
01
0/
0.
0!
0"
0#
1$
#3250000
1!
1.
12
11
1"
#3260000
0!
02
01
0/
0.
0"
1#
#3270000
1/
12
11
1"
#3280000
13
02
01
1/
0.
1!
1&
0"
0#
0$
b101001 %
#3290000
0!
0/
1.
03
12
11
1"
#3300000
0!
13
02
01
0/
0.
0"
1#
#3310000
1!
1/
03
12
11
1"
#3320000
13
02
01
1/
0.
0!
0"
0#
1$
#3330000
1!
0/
1.
03
12
11
1"
#3340000
0!
13
02
01
0/
0.
0"
1#
#3350000
1/
03
12
11
1"
#3360000
02
01
0/
0.
0!
0&
1'
0"
0#
0$
b101010 %
#3370000
1!
1/
1.
13
12
11
1"
#3380000
0!
0/
03
02
01
0.
0"
1#
#3390000
1!
1/
13
12
11
1"
#3400000
0/
03
02
01
0.
0!
0"
0#
1$
#3410000
1!
1/
1.
13
12
11
1"
#3420000
0/
0!
03
02
01
0.
0"
1#
#3430000
1/
13
12
11
1"
#3440000
02
01
0.
1!
1&
0"
0#
0$
b101011 %
#3450000
1.
12
11
1"
#3460000
0!
0/
02
01
0.
0"
1#
#3470000
1!
1/
12
11
1"
#3480000
02
01
0.
0!
0"
0#
1$
#3490000
1!
1.
12
11
1"
#3500000
0/
0!
02
01
0.
0"
1#
#3510000
1/
12
11
1"
#3520000
0/
03
01
0.
0!
0&
0'
1(
0"
0#
0$
b101100 %
#3530000
1.
11
1"
#3540000
1!
01
1/
0.
0"
1#
#3550000
11
1"
#3560000
01
0/
0.
0!
0"
0#
1$
#3570000
1!
1.
11
1"
#3580000
0!
01
1/
0.
0"
1#
#3590000
11
1"
#3600000
13
01
1/
0.
1!
1&
0"
0#
0$
b101101 %
#3610000
0!
0/
1.
03
11
1"
#3620000
1!
13
01
1/
0.
0"
1#
#3630000
03
11
1"
#3640000
13
01
1/
0.
0!
0"
0#
1$
#3650000
1!
0/
1.
03
11
1"
#3660000
0!
13
01
1/
0.
0"
1#
#3670000
03
11
1"
#3680000
01
0/
0.
0!
0&
1'
0"
0#
0$
b101110 %
#3690000
1!
1/
1.
13
11
1"
#3700000
03
01
0.
0"
1#
#3710000
13
11
1"
#3720000
0/
03
01
0.
0!
0"
0#
1$
#3730000
1!
1/
1.
13
11
1"
#3740000
0!
03
01
0.
0"
1#
#3750000
13
11
1"
#3760000
01
0.
1!
1&
0"
0#
0$
b101111 %
#3770000
1.
11
1"
#3780000
01
0.
0"
1#
#3790000
11
1"
#3800000
01
0.
0!
0"
0#
1$
#3810000
1!
1.
11
1"
#3820000
0!
01
0.
0"
1#
#3830000
11
1"
#3840000
0/
03
02
1.
0!
0&
0'
0(
0)
1*
0"
0#
0$
b110000 %
#3850000
1"
#3860000
0.
0"
1#
#3870000
1"
#3880000
1!
1.
0"
0#
1$
#3890000
1"
#3900000
0!
0.
0"
1#
#3910000
1"
#3920000
1!
1/
13
1.
1&
0"
0#
0$
b110001 %
#3930000
0!
0/
03
1"
#3940000
13
0.
0"
1#
#3950000
03
1"
#3960000
1/
1!
13
1.
0"
0#
1$
#3970000
0/
03
1"
#3980000
0!
13
0.
0"
1#
#3990000
03
1"
#4000000
1.
0&
1'
0"
0#
0$
b110010 %
#4010000
1!
1/
13
1"
#4020000
0!
03
0/
0.
0"
1#
#4030000
13
1"
#4040000
1!
03
0/
1.
0"
0#
1$
#4050000
1/
13
1"
#4060000
0!
03
0/
0.
0"
1#
#4070000
13
1"
#4080000
1!
1/
1.
1&
0"
0#
0$
b110011 %
#4090000
1"
#4100000
0!
0/
0.
0"
1#
#4110000
1"
#4120000
1!
1/
1.
0"
0#
1$
#4130000
1"
#4140000
0!
0/
0.
0"
1#
#4150000
1"
#4160000
0!
03
12
0/
1.
0&
0'
1(
0"
0#
0$
b110100 %
#4170000
02
1"
#4180000
1!
1/
12
0.
0"
1#
#4190000
0!
0/
02
1"
#4200000
1!
12
1.
0"
0#
1$
#4210000
02
1"
#4220000
1/
0!
12
0.
0"
1#
#4230000
0/
02
1"
#4240000
1!
1/
13
12
1.
1&
0"
0#
0$
b110101 %
#4250000
0!
0/
03
02
1"
#4260000
1!
1/
13
12
0.
0"
1#
#4270000
0!
0/
03
02
1"
#4280000
1/
1!
13
12
1.
0"
0#
1$
#4290000
0/
03
02
1"
#4300000
1/
0!
13
12
0.
0"
1#
#4310000
0/
03
02
1"
#4320000
12
1.
0&
1'
0"
0#
0$
b110110 %
#4330000
1!
1/
13
02
1"
#4340000
1!
03
12
1/
0.
0"
1#
#4350000
0!
0/
13
02
1"
#4360000
1!
03
12
0/
1.
0"
0#
1$
#4370000
1/
13
02
1"
#4380000
0!
03
12
1/
0.
0"
1#
#4390000
0/
13
02
1"
#4400000
1!
12
1/
1.
1&
0"
0#
0$
b110111 %
#4410000
02
1"
#4420000
1!
12
1/
0.
0"
1#
#4430000
0!
0/
02
1"
#4440000
1!
12
1/
1.
0"
0#
1$
#4450000
02
1"
#4460000
0!
12
1/
0.
0"
1#
#4470000
0/
02
1"
#4480000
0!
03
0/
1.
0&
0'
0(
1)
0"
0#
0$
b111000 %
#4490000
12
1"
#4500000
0!
02
0/
0.
0"
1#
#4510000
1!
1/
12
1"
#4520000
02
0/
1.
1!
0"
0#
1$
#4530000
12
1"
#4540000
0!
02
0/
0.
0"
1#
#4550000
1/
12
1"
#4560000
13
02
1/
1.
1!
1&
0"
0#
0$
b111001 %
#4570000
0!
0/
03
12
1"
#4580000
0!
13
02
0/
0.
0"
1#
#4590000
1!
1/
03
12
1"
#4600000
13
02
1/
1.
1!
0"
0#
1$
#4610000
0/
03
12
1"
#4620000
0!
13
02
0/
0.
0"
1#
#4630000
1/
03
12
1"
#4640000
02
0/
1.
0!
0&
1'
0"
0#
0$
b111010 %
#4650000
1!
1/
13
12
1"
#4660000
0!
0/
03
02
0.
0"
1#
#4670000
1!
1/
13
12
1"
#4680000
0/
03
02
1.
1!
0"
0#
1$
#4690000
1/
13
12
1"
#4700000
0/
0!
03
02
0.
0"
1#
#4710000
1/
13
12
1"
#4720000
02
1.
1!
1&
0"
0#
0$
b111011 %
#4730000
12
1"
#4740000
0!
0/
02
0.
0"
1#
#4750000
1!
1/
12
1"
#4760000
02
1.
1!
0"
0#
1$
#4770000
12
1"
#4780000
0/
0!
02
0.
0"
1#
#4790000
1/
12
1"
#4800000
0/
03
1.
0!
0&
0'
1(
0"
0#
0$
b111100 %
#4810000
1"
#4820000
1!
1/
0.
0"
1#
#4830000
1"
#4840000
0/
1.
1!
0"
0#
1$
#4850000
1"
#4860000
0!
1/
0.
0"
1#
#4870000
1"
#4880000
13
1/
1.
1!
1&
0"
0#
0$
b111101 %
#4890000
0!
0/
03
1"
#4900000
1!
13
1/
0.
0"
1#
#4910000
03
1"
#4920000
13
1/
1.
1!
0"
0#
1$
#4930000
0/
03
1"
#4940000
0!
13
1/
0.
0"
1#
#4950000
03
1"
#4960000
0/
1.
0!
0&
1'
0"
0#
0$
b111110 %
#4970000
1!
1/
13
1"
#4980000
03
0.
0"
1#
#4990000
13
1"
#5000000
0/
03
1.
1!
0"
0#
1$
#5010000
1/
13
1"
#5020000
0!
03
0.
0"
1#
#5030000
13
1"
#5040000
1.
1!
1&
0"
0#
0$
b111111 %
#5050000
1"
#5060000
0.
0"
1#
#5070000
1"
#5080000
1.
1!
0"
0#
1$
#5090000
1"
#5100000
0!
0.
0"
1#
#5110000
1"
#5120000
0/
03
02
01
10
0.
0!
0&
0'
0(
0)
0*
0+
1,
0"
0#
0$
b1000000 %
#5130000
00
1"
#5140000
1.
10
0"
1#
#5150000
0.
00
1"
#5160000
10
0"
0#
1$
#5170000
00
1"
#5180000
1!
1.
10
0"
1#
#5190000
0!
0.
00
1"
#5200000
1!
1/
13
10
1&
0"
0#
0$
b1000001 %
#5210000
0!
0/
03
00
1"
#5220000
1.
13
10
0"
1#
#5230000
0.
03
00
1"
#5240000
1/
13
10
0"
0#
1$
#5250000
0/
03
00
1"
#5260000
1!
1.
13
10
0"
1#
#5270000
0!
0.
03
00
1"
#5280000
10
0&
1'
0"
0#
0$
b1000010 %
#5290000
1!
1/
13
00
1"
#5300000
1.
0!
03
10
0/
0"
1#
#5310000
0.
13
00
1"
#5320000
03
10
0/
0"
0#
1$
#5330000
1/
13
00
1"
#5340000
1!
1.
03
10
0/
0"
1#
#5350000
0!
0.
13
00
1"
#5360000
1!
10
1/
1&
0"
0#
0$
b1000011 %
#5370000
00
1"
#5380000
1.
0!
10
0/
0"
1#
#5390000
0.
00
1"
#5400000
10
1/
0"
0#
1$
#5410000
00
1"
#5420000
1!
1.
10
0/
0"
1#
#5430000
0!
0.
00
1"
#5440000
0!
03
12
10
0/
0&
0'
1(
0"
0#
0$
b1000100 %
#5450000
02
00
1"
#5460000
1!
1/
1.
12
10
0"
1#
#5470000
0!
0/
0.
02
00
1"
#5480000
12
10
0"
0#
1$
#5490000
02
00
1"
#5500000
1!
1/
1.
12
10
0"
1#
#5510000
0!
0/
0.
02
00
1"
#5520000
1!
1/
13
12
10
1&
0"
0#
0$
b1000101 %
#5530000
0!
0/
03
02
00
1"
#5540000
1!
1/
1.
13
12
10
0"
1#
#5550000
0!
0/
0.
03
02
00
1"
#5560000
1/
13
12
10
0"
0#
1$
#5570000
0/
03
02
00
1"
#5580000
1!
1/
1.
13
12
10
0"
1#
#5590000
0!
0/
0.
03
02
00
1"
#5600000
12
10
0&
1'
0"
0#
0$
b1000110 %
#5610000
1!
1/
13
02
00
1"
#5620000
1.
1!
03
12
10
1/
0"
1#
#5630000
0!
0/
0.
13
02
00
1"
#5640000
03
12
10
0/
0"
0#
1$
#5650000
1/
13
02
00
1"
#5660000
1!
1.
03
12
10
1/
0"
1#
#5670000
0!
0/
0.
13
02
00
1"
#5680000
1!
12
10
1/
1&
0"
0#
0$
b1000111 %
#5690000
02
00
1"
#5700000
1.
1!
12
10
1/
0"
1#
#5710000
0!
0/
0.
02
00
1"
#5720000
12
10
1/
0"
0#
1$
#5730000
02
00
1"
#5740000
1!
1.
12
10
1/
0"
1#
#5750000
0!
0/
0.
02
00
1"
#5760000
0!
03
10
0/
0&
0'
0(
1)
0"
0#
0$
b1001000 %
#5770000
12
00
1"
#5780000
1.
0!
02
10
0/
0"
1#
#5790000
1!
1/
0.
12
00
1"
#5800000
02
10
0/
0!
0"
0#
1$
#5810000
12
00
1"
#5820000
1!
1.
02
10
0/
0"
1#
#5830000
0!
1/
0.
12
00
1"
#5840000
13
02
10
1/
1!
1&
0"
0#
0$
b1001001 %
#5850000
0!
0/
03
12
00
1"
#5860000
1.
0!
13
02
10
0/
0"
1#
#5870000
1!
1/
0.
03
12
00
1"
#5880000
13
02
10
1/
0!
0"
0#
1$
#5890000
0/
03
12
00
1"
#5900000
1!
1.
13
02
10
0/
0"
1#
#5910000
0!
1/
0.
03
12
00
1"
#5920000
02
10
0/
0!
0&
1'
0"
0#
0$
b1001010 %
#5930000
1!
1/
13
12
00
1"
#5940000
0!
0/
1.
03
02
10
0"
1#
#5950000
1!
1/
0.
13
12
00
1"
#5960000
0/
03
02
10
0!
0"
0#
1$
#5970000
1/
13
12
00
1"
#5980000
1!
0/
1.
03
02
10
0"
1#
#5990000
0!
1/
0.
13
12
00
1"
#6000000
02
10
1!
1&
0"
0#
0$
b1001011 %
#6010000
12
00
1"
#6020000
0!
0/
1.
02
10
0"
1#
#6030000
1!
1/
0.
12
00
1"
#6040000
02
10
0!
0"
0#
1$
#6050000
12
00
1"
#6060000
1!
0/
1.
02
10
0"
1#
#6070000
0!
1/
0.
12
00
1"
#6080000
0/
03
10
0!
0&
0'
1(
0"
0#
0$
b1001100 %
#6090000
00
1"
#6100000
1.
1!
10
1/
0"
1#
#6110000
0.
00
1"
#6120000
10
0/
0!
0"
0#
1$
#6130000
00
1"
#6140000
1!
1.
10
1/
0"
1#
#6150000
0!
0.
00
1"
#6160000
13
10
1/
1!
1&
0"
0#
0$
b1001101 %
#6170000
0!
0/
03
00
1"
#6180000
1.
1!
13
10
1/
0"
1#
#6190000
0.
03
00
1"
#6200000
13
10
1/
0!
0"
0#
1$
#6210000
0/
03
00
1"
#6220000
1!
1.
13
10
1/
0"
1#
#6230000
0!
0.
03
00
1"
#6240000
10
0/
0!
0&
1'
0"
0#
0$
b1001110 %
#6250000
1!
1/
13
00
1"
#6260000
1.
03
10
0"
1#
#6270000
0.
13
00
1"
#6280000
0/
03
10
0!
0"
0#
1$
#6290000
1/
13
00
1"
#6300000
1!
1.
03
10
0"
1#
#6310000
0!
0.
13
00
1"
#6320000
10
1!
1&
0"
0#
0$
b1001111 %
#6330000
00
1"
#6340000
1.
10
0"
1#
#6350000
0.
00
1"
#6360000
10
0!
0"
0#
1$
#6370000
00
1"
#6380000
1!
1.
10
0"
1#
#6390000
0!
0.
00
1"
#6400000
0/
1.
03
02
11
10
0!
0&
0'
0(
0)
1*
0"
0#
0$
b1010000 %
#6410000
0.
01
00
1"
#6420000
1.
11
10
0"
1#
#6430000
0.
01
00
1"
#6440000
1!
1.
11
10
0"
0#
1$
#6450000
0!
0.
01
00
1"
#6460000
1!
1.
11
10
0"
1#
#6470000
0!
0.
01
00
1"
#6480000
1!
1/
1.
13
11
10
1&
0"
0#
0$
b1010001 %
#6490000
0!
0/
0.
03
01
00
1"
#6500000
1.
13
11
10
0"
1#
#6510000
0.
03
01
00
1"
#6520000
1!
1/
1.
13
11
10
0"
0#
1$
#6530000
0!
0/
0.
03
01
00
1"
#6540000
1!
1.
13
11
10
0"
1#
#6550000
0!
0.
03
01
00
1"
#6560000
1.
11
10
0&
1'
0"
0#
0$
b1010010 %
#6570000
1!
1/
0.
13
01
00
1"
#6580000
1.
0!
03
11
10
0/
0"
1#
#6590000
0.
13
01
00
1"
#6600000
1!
1.
03
11
10
0/
0"
0#
1$
#6610000
0!
1/
0.
13
01
00
1"
#6620000
1!
1.
03
11
10
0/
0"
1#
#6630000
0!
0.
13
01
00
1"
